jplaw/__init__.py
jplaw/api_paths.py
jplaw/comment.py
jplaw/community.py
jplaw/emoji.py
jplaw/lemmy.py
jplaw/post.py
jplaw/private_message.py
jplaw/requestor.py
jplaw/site.py
jplaw/user.py
jplaw/types/__init__.py
jplaw/types/comment_sort_type.py
jplaw/types/http_type.py
jplaw/types/listing_type.py
jplaw/types/modlog_action_type.py
jplaw/types/post_feature_type.py
jplaw/types/registration_mode.py
jplaw/types/search_type.py
jplaw/types/sort_type.py
jplaw/types/subscribed_type.py
jplaw-0.1.10.dist-info/LICENSE
jplaw-0.1.10.dist-info/METADATA
jplaw-0.1.10.dist-info/WHEEL
jplaw-0.1.10.dist-info/top_level.txt
jplaw-0.1.10.dist-info/RECORD
