Metadata-Version: 2.1
Name: jplaw
Version: 0.1.10
Summary: A python wrapper for the lemmy HTTP API. Forked from plaw by Benjamin Jablonski (benja810)
Author-email: Amar Persaud <tehspartaa@gmail.com>
Project-URL: Homepage, https://github.com/amarpersaud/python-jplaw
Project-URL: Bug Tracker, https://github.com/amarpersaud/python-jplaw/issues
Classifier: Programming Language :: Python :: 3
Classifier: License :: OSI Approved :: MIT License
Classifier: Operating System :: OS Independent
Requires-Python: >=3.7
License-File: LICENSE
